[
 {
  "date": "Mon, 09 Jun 2014 22:36:00 EST", 
  "link": "http://cn.engadget.com/2014/06/09/youtube-playstation-4/", 
  "description": "<p>分类: <a href=\"http://cn.engadget.com/category/gaming/\" rel=\"tag\">游戏产品</a></p><div style=\"text-align: center;\"><a href=\"http://cn.engadget.com/2014/06/09/youtube-playstation-4\"><img alt=\"\" src=\"http://o.aolcdn.com/hss/storage/midas/6b7385294e5ca8911ae69be5e0aa60a3/200253412/lb2-3756.jpg\" style=\"width: 620px; height: 413px;\" /></a></div>\n<br />\nSCE 的新主管 Shawn Layden 在今年 <a href=\"http://cn.engadget.com/tag/E3/\">E3</a> 的舞台上，宣布了影音分享平台 <a href=\"http://cn.engadget.com/tag/YouTube/\">YouTube</a> 将登陆 <a href=\"http://cn.engadget.com/tag/PS4/\">PS4</a> 主机平台的消息，时间则是在今年年底前。Layden 还公布了有超过 95% 的主机使用 PSN 服务，并且常常使用 DualShock 4 上的分享按钮 -- 要数字？好吧，总共超过 2.2 亿次（看来大家是真的卯起来按了 XD）。加入 YouTube 支援的 PS4 将提供更简易的游戏影片上传分享功能，没错，就是那颗 Share 钮，就用力按下去吧！<br />\n<br />\n引用来源：<a href=\"http://www.engadget.com/2014/06/09/youtube-playstation-4/\">Engadget</a><p><h6 style=\"clear: both; padding: 8px 0 0 0; height: 2px; font-size: 1px; border: 0; margin: 0; padding: 0;\"></h6><a href=\"http://cn.engadget.com/2014/06/09/youtube-playstation-4/\" rel=\"bookmark\" title=\"Permanent link to this entry\">此文章网址</a>&nbsp;|&nbsp;<a href=\"http://cn.engadget.com/forward/20909564/\" title=\"Send this entry to a friend via email\">转寄此文章</a>&nbsp;|&nbsp;<a href=\"http://cn.engadget.com/2014/06/09/youtube-playstation-4/#comments\" title=\"View reader comments on this entry\">回应</a><hr size=\"1\" />", 
  "title": "分享更容易了，YouTube 将于年底登陆 PlayStation 4"
 }, 
 {
  "date": "Mon, 09 Jun 2014 22:21:00 EST", 
  "link": "http://cn.engadget.com/2014/06/09/xbox-one-9-23-hk/", 
  "description": "<p>分类: <a href=\"http://cn.engadget.com/category/gaming/\" rel=\"tag\">游戏产品</a></p><div style=\"text-align: center;\"><a href=\"http://cn.engadget.com/2014/06/09/xbox-one-9-23-hk/\"><img alt=\"\" src=\"http://o.aolcdn.com/hss/storage/midas/f9f6f5363e232c04131ccb55cd90e189/200080817/1-xb1review_hedimg_630px_take1.jpg\" style=\"width: 620px; height: 353px;\" /></a></div>\n<br />\nMicrosoft 刚刚宣布 Xbox One 将於 9 月 23 日正式在香港发售，不含 Kinect 版本售价 HK$3,380，含 Kinect 版本售价为 HK$4,180。与美国 E3 刚刚公布不含 Kinect 版本的 Xbox One 一样，在香港发售的 Xbox One 套装将包括 500GB 硬盘丶蓝光播放器丶内建 Wi-Fi丶Xbox One 无线手掣及 14 天免费的 Xbox LIVE 金会员试用服务。至於包含 Kinect 的 Xbox One 套装则可以同时玩到体感操控丶生物辨识登入丶手掣配对丶Skype 视像通话丶扫描 QR Codes功能，以及於《Kinect Sports: Rivals》丶《Dead Rising 3》及《Project Spark》等游戏中使用 Kinect 特有的游戏功能。Microsoft 同时宣布将於香港发售《Forza Horizon 2》丶《Halo: The Master Chief Collection》，後者更内附《Halo 5: Guardians》之多人模式 Beta 版。<p><h6 style=\"clear: both; padding: 8px 0 0 0; height: 2px; font-size: 1px; border: 0; margin: 0; padding: 0;\"></h6><a href=\"http://cn.engadget.com/2014/06/09/xbox-one-9-23-hk/\" rel=\"bookmark\" title=\"Permanent link to this entry\">此文章网址</a>&nbsp;|&nbsp;<a href=\"http://cn.engadget.com/forward/20909567/\" title=\"Send this entry to a friend via email\">转寄此文章</a>&nbsp;|&nbsp;<a href=\"http://cn.engadget.com/2014/06/09/xbox-one-9-23-hk/#comments\" title=\"View reader comments on this entry\">回应</a><hr size=\"1\" />", 
  "title": "Xbox One 9 月 23 日香港发售，不含 Kinect 版本售价 HK$3,380"
 }
]