[
 {
  "date": "Wed, 19 Aug 2015 21:00:00 -0400", 
  "link": "http://cn.engadget.com/2015/08/19/skype-android-ringtones-and-photo-forwarding/?ncid=rss_truncated", 
  "description": "<img src=\"http://o.aolcdn.com/hss/storage/midas/55cf4f4c232c1cf9eea2372e6e6d2ffe/202304509/skype-sign-in-android_thumbnail.jpg\" />各位 Android 版 Skype 的用户，你平时会想要为某个特定好友设定专属的铃声吗？如果是的话，那不久前上线的新版本应该会很对你的胃口。在此次更新中，微软的开发团队终于加入了这项在电话上早已很常见的功能。除此之外，现在在聊天中收到的照片还可以直接转发给其他 Skype 好友，相较过去省掉了好几个步骤呢。目前新版已在 Google Play 中上线，有需要的朋友就快去下载试试看吧。...", 
  "title": "Android 版 Skype 迎来专属铃声和照片转发功能"
 }, 
 {
  "date": "Wed, 19 Aug 2015 20:00:00 -0400", 
  "link": "http://cn.engadget.com/2015/08/19/windows-10-next-preview-build/?ncid=rss_truncated", 
  "description": "<img src=\"http://o.aolcdn.com/hss/storage/midas/43ec055fe8627c7da9f1448710cd1476/202497031/Windows%2B10%2Breview%2Bfullbleed_thumbnail.jpg\" />虽说距离 Windows 10 正式上线的日子才过去没多久，但微软显然没有闲着，这不，发售后的首个新版本预览现在已经准备就绪了。如果你是 Windows Insider 计划的一份子，那全新的 Preview Build 10525 应该很快就会通过 Windows 更新被自动下载到你的电脑之上。这次有两个比较明显的变化，一是可以对任务列的颜色进行调整，另外一项，则是大幅改善的内存管理方案。不过与此同时，视频播放和网络分享功能似乎都出了点问题，但如果你不是很在意这些的话，就放心地去升级吧。...", 
  "title": "Windows 10 正式开卖后的首个新版本预览已就绪"
 }
]