[
 {
  "date": "Wed, 06 May 2020 13:00:00 +0000", 
  "link": "https://cn.engadget.com/cn-2020-05-06-nfc-forum-wireless-charging-for-small-devices.html", 
  "description": "这几年支持高功率无线反向充电的设备我们其实已经见过不少，不过它们大多定位高端，而 NFC 论坛显然认为类似特性也值得向更大众的产品推广。于是日前他们公布了新的无线充电规范（Wireless Charging Specification），基于该方案的手机、平板、笔记本、充电器甚至游戏手柄只要凭借单天线设计，就能为兼容的设备进行功率最高 1W 的无线充电了。  当然，NFC 原本的近场通讯功能并不会受到影响。而 1W", 
  "title": "未来你能通过手机 NFC 为耳机、手表进行低功率无线充电"
 }, 
 {
  "date": "Wed, 06 May 2020 12:00:00 +0000", 
  "link": "https://cn.engadget.com/cn-2020-05-06-airbnb-to-lay-off-25-percent-of-workforce.html", 
  "description": "新冠疫情持续冲击着各行各业，但受创最重的非旅游业莫属。为了能确保公司撑过这艰难的时期，Airbnb 向 Techcrunch 确认了自己将裁员高达 1,900 人，略高于公司总人数的 25%，以在疫情期间撙节开支。Airbnb 并没有提被裁员的员工在各国的比例，但 CEO Brian Chesky 在备忘录中表示自家的交通、旅游节目、奢华住宿和旅馆合作等较边「周边」的业务，会是影响最重的区域，务求让 Airbnb 的商业活动更专注在核心上。  被解雇的员工将获得 14", 
  "title": "Airbnb 将解雇高达 25% 的员工来确保公司能撑过疫情"
 }
]